mvn_tree_visualizer/__init__.py
mvn_tree_visualizer/__main__.py
mvn_tree_visualizer/cli.py
mvn_tree_visualizer/diagram.py
mvn_tree_visualizer/enhanced_template.py
mvn_tree_visualizer/exceptions.py
mvn_tree_visualizer/file_watcher.py
mvn_tree_visualizer/get_dependencies_in_one_file.py
mvn_tree_visualizer/themes.py
mvn_tree_visualizer/utils.py
mvn_tree_visualizer/validation.py
mvn_tree_visualizer/outputs/html_output.py
mvn_tree_visualizer/outputs/json_output.py
mvn_tree_visualizer-1.8.5.dist-info/METADATA
mvn_tree_visualizer-1.8.5.dist-info/WHEEL
mvn_tree_visualizer-1.8.5.dist-info/entry_points.txt
mvn_tree_visualizer-1.8.5.dist-info/licenses/LICENSE
mvn_tree_visualizer-1.8.5.dist-info/RECORD
