Metadata-Version: 2.4
Name: mvn-tree-visualizer
Version: 1.8.5
Summary: A simple command line tool to visualize the dependency tree of a Maven project in a graphical format.
Project-URL: source, https://github.com/dyka3773/mvn-tree-visualizer
Author-email: Iraklis Konsoulas <dyka3773@gmail.com>
License-Expression: MIT
License-File: LICENSE
Keywords: cli,command-line,dependency,graph,maven,mermaid,tool,tree,visualization
Classifier: Development Status :: 5 - Production/Stable
Classifier: Intended Audience :: Developers
Classifier: Programming Language :: Python :: 3
Classifier: Programming Language :: Python :: 3.10
Classifier: Programming Language :: Python :: 3.11
Classifier: Programming Language :: Python :: 3.12
Classifier: Programming Language :: Python :: 3.13
Classifier: Topic :: Software Development :: Build Tools
Classifier: Typing :: Typed
Requires-Python: >=3.10
Requires-Dist: jinja2>=3.1.6
Requires-Dist: watchdog>=6.0.0
